robodesk
