Metadata-Version: 2.1
Name: robodesk
Version: 0.0.5
Summary: Multi-task reinforcement learning benchmark.
Home-page: https://github.com/google-research/robodesk
Author: Harini Kannan
Author-email: hkannan@google.com
License: UNKNOWN
Platform: UNKNOWN
Classifier: Intended Audience :: Science/Research
Classifier: Intended Audience :: Developers
Classifier: License :: OSI Approved :: MIT License
Classifier: Programming Language :: Python :: 3
Classifier: Topic :: Games/Entertainment
Classifier: Topic :: Scientific/Engineering :: Artificial Intelligence
